f2t2f/__init__.py
f2t2f/cli.py
f2t2f/config.py
f2t2f/file_filter.py
f2t2f/folder_ops.py
f2t2f/text_formatter.py
f2t2f-0.3.9.dist-info/licenses/LICENSE
f2t2f-0.3.9.dist-info/METADATA
f2t2f-0.3.9.dist-info/WHEEL
f2t2f-0.3.9.dist-info/entry_points.txt
f2t2f-0.3.9.dist-info/top_level.txt
f2t2f-0.3.9.dist-info/RECORD
