Metadata-Version: 2.4
Name: f2t2f
Version: 0.3.9
Summary: A CLI tool to capture entire folders, including file content, as structured JSON or text.
Home-page: https://github.com/vovaauer/f2t2f
Author: Vova Auer
Author-email: mail@vovaauer.com
License: MIT
Classifier: Programming Language :: Python :: 3
Classifier: License :: OSI Approved :: MIT License
Classifier: Operating System :: OS Independent
Classifier: Topic :: Utilities
Classifier: Environment :: Console
Requires-Python: >=3.7
License-File: LICENSE
Requires-Dist: click
Requires-Dist: pyperclip
Requires-Dist: platformdirs
Requires-Dist: patch
Dynamic: author
Dynamic: author-email
Dynamic: classifier
Dynamic: description
Dynamic: description-content-type
Dynamic: home-page
Dynamic: license
Dynamic: license-file
Dynamic: requires-dist
Dynamic: requires-python
Dynamic: summary
